crawl4weibo/__init__.py
crawl4weibo/core/__init__.py
crawl4weibo/core/client.py
crawl4weibo/exceptions/__init__.py
crawl4weibo/exceptions/base.py
crawl4weibo/models/__init__.py
crawl4weibo/models/comment.py
crawl4weibo/models/post.py
crawl4weibo/models/user.py
crawl4weibo/utils/__init__.py
crawl4weibo/utils/cookie_fetcher.py
crawl4weibo/utils/downloader.py
crawl4weibo/utils/logger.py
crawl4weibo/utils/parser.py
crawl4weibo/utils/proxy.py
crawl4weibo/utils/proxy_parsers.py
crawl4weibo/utils/rate_limit.py
crawl4weibo-0.3.3.dist-info/licenses/LICENSE
crawl4weibo-0.3.3.dist-info/METADATA
crawl4weibo-0.3.3.dist-info/WHEEL
crawl4weibo-0.3.3.dist-info/top_level.txt
crawl4weibo-0.3.3.dist-info/RECORD
