Metadata-Version: 2.4
Name: crawl4weibo
Version: 0.3.3
Summary: A professional Weibo crawler library
Author-email: Kritoooo <krito2023@gmail.com>
License: MIT
Project-URL: Homepage, https://github.com/Praeviso/crawl4weibo
Classifier: Development Status :: 3 - Alpha
Classifier: Intended Audience :: Developers
Classifier: License :: OSI Approved :: MIT License
Classifier: Operating System :: OS Independent
Classifier: Programming Language :: Python :: 3
Classifier: Programming Language :: Python :: 3.9
Classifier: Programming Language :: Python :: 3.9
Classifier: Programming Language :: Python :: 3.10
Classifier: Programming Language :: Python :: 3.11
Classifier: Programming Language :: Python :: 3.12
Requires-Python: >=3.9
License-File: LICENSE
Requires-Dist: requests>=2.25.0
Requires-Dist: lxml>=4.6.0
Requires-Dist: tqdm>=4.60.0
Requires-Dist: python-dateutil>=2.8.0
Requires-Dist: playwright>=1.48.0
Provides-Extra: dev
Requires-Dist: pytest>=6.0; extra == "dev"
Requires-Dist: pytest-cov; extra == "dev"
Requires-Dist: black; extra == "dev"
Requires-Dist: isort; extra == "dev"
Requires-Dist: flake8; extra == "dev"
Dynamic: license-file
